MANIFEST.in
README.md
setup.py
bin/python_qt_live_coding
examples/integrated/live.qml
examples/integrated/main.py
examples/integrated/main.qml
examples/integrated/myapp/MainPanel.qml
examples/integrated/myapp/qmldir
examples/standalone/MainScreen.qml
examples/standalone/qmldir
examples/standalone/module/__init__.py
examples/standalone/module/calculator.py
src/livecoding/FileSelectionDialog.qml
src/livecoding/LiveCodingPanel.qml
src/livecoding/__init__.py
src/livecoding/filewatcher.py
src/livecoding/gui.py
src/livecoding/icon.png
src/livecoding/live.qml
src/livecoding/live_coding_helper.py
src/livecoding/moduleloader.py
src/livecoding/projectbrowser.py
src/livecoding/pythonreloader.py
src/livecoding/qmldir
src/livecoding/register_qml_types.py
src/python_qt_live_coding.egg-info/PKG-INFO
src/python_qt_live_coding.egg-info/SOURCES.txt
src/python_qt_live_coding.egg-info/dependency_links.txt
src/python_qt_live_coding.egg-info/requires.txt
src/python_qt_live_coding.egg-info/top_level.txt