Metadata-Version: 2.1
Name: python-qt-live-coding
Version: 0.4.3
Summary: Live coding for Python, Qt and QML
Home-page: https://github.com/machinekoder/python-qt-live-coding/
Author: Alexander Rössler
Author-email: alex@machinekoder.com
License: MIT
Platform: UNKNOWN
Provides-Extra: dev
